clanim/__init__.py
clanim/alnum.py
clanim/big_char.py
clanim/cli.py
clanim/decorator.py
clanim/multiline.py
clanim/singleline.py
clanim/util.py
clanim/animation/__init__.py
clanim/animation/alnum.py
clanim/animation/animation.py
clanim/animation/big_char.py
clanim/animation/multiline.py
clanim/animation/singleline.py
clanim-0.3.0.dist-info/METADATA
clanim-0.3.0.dist-info/RECORD
clanim-0.3.0.dist-info/WHEEL
clanim-0.3.0.dist-info/top_level.txt
