Metadata-Version: 2.1
Name: clanim
Version: 0.3.0
Summary: Command line animations built with clanimtk.
Home-page: https://github.com/slarse/clanim
Author: Simon Larsén
Author-email: slarse@kth.se
License: MIT License
Requires-Dist: clanimtk
